multiversx_sdk/__init__.py
multiversx_sdk/py.typed
multiversx_sdk/abi/__init__.py
multiversx_sdk/abi/abi.py
multiversx_sdk/abi/abi_definition.py
multiversx_sdk/abi/address_value.py
multiversx_sdk/abi/array_value.py
multiversx_sdk/abi/bigint_value.py
multiversx_sdk/abi/biguint_value.py
multiversx_sdk/abi/bool_value.py
multiversx_sdk/abi/bytes_value.py
multiversx_sdk/abi/code_metadata_value.py
multiversx_sdk/abi/codec.py
multiversx_sdk/abi/constants.py
multiversx_sdk/abi/counted_variadic_values.py
multiversx_sdk/abi/enum_value.py
multiversx_sdk/abi/explicit_enum_value.py
multiversx_sdk/abi/fields.py
multiversx_sdk/abi/interface.py
multiversx_sdk/abi/list_value.py
multiversx_sdk/abi/managed_decimal_signed_value.py
multiversx_sdk/abi/managed_decimal_value.py
multiversx_sdk/abi/multi_value.py
multiversx_sdk/abi/option_value.py
multiversx_sdk/abi/optional_value.py
multiversx_sdk/abi/parts.py
multiversx_sdk/abi/serializer.py
multiversx_sdk/abi/shared.py
multiversx_sdk/abi/small_int_values.py
multiversx_sdk/abi/string_value.py
multiversx_sdk/abi/struct_value.py
multiversx_sdk/abi/token_identifier_value.py
multiversx_sdk/abi/tuple_value.py
multiversx_sdk/abi/type_formula.py
multiversx_sdk/abi/type_formula_parser.py
multiversx_sdk/abi/typesystem.py
multiversx_sdk/abi/variadic_values.py
multiversx_sdk/account_management/__init__.py
multiversx_sdk/account_management/account_controller.py
multiversx_sdk/account_management/account_transactions_factory.py
multiversx_sdk/accounts/__init__.py
multiversx_sdk/accounts/account.py
multiversx_sdk/accounts/ledger_account.py
multiversx_sdk/builders/__init__.py
multiversx_sdk/builders/token_transfers_data_builder.py
multiversx_sdk/core/__init__.py
multiversx_sdk/core/address.py
multiversx_sdk/core/base_controller.py
multiversx_sdk/core/base_factory.py
multiversx_sdk/core/bech32.py
multiversx_sdk/core/code_metadata.py
multiversx_sdk/core/config.py
multiversx_sdk/core/constants.py
multiversx_sdk/core/errors.py
multiversx_sdk-2.3.3.dist-info/METADATA
multiversx_sdk-2.3.3.dist-info/WHEEL
multiversx_sdk-2.3.3.dist-info/licenses/LICENSE
multiversx_sdk-2.3.3.dist-info/RECORD
