Metadata-Version: 2.4
Name: multiversx-sdk
Version: 2.3.3
Summary: The MultiversX Python SDK.
Project-URL: Homepage, https://github.com/multiversx/mx-sdk-py
Author: MultiversX
License-Expression: MIT
License-File: LICENSE
Classifier: License :: OSI Approved :: MIT License
Classifier: Operating System :: OS Independent
Classifier: Programming Language :: Python :: 3
Requires-Python: >=3.8
Requires-Dist: cryptography==44.0.1
Requires-Dist: mnemonic==0.21
Requires-Dist: protobuf==6.31.1
Requires-Dist: pycryptodomex==3.19.1
Requires-Dist: pynacl==1.5.0
Requires-Dist: requests<3.0.0,>=2.32.0
Provides-Extra: ledger
Requires-Dist: ledgercomm[hid]; extra == 'ledger'
